avocado_result_mail/__init__.py
avocado_result_mail/result_mail.py
avocado_framework_plugin_result_mail-113.0.dist-info/METADATA
avocado_framework_plugin_result_mail-113.0.dist-info/WHEEL
avocado_framework_plugin_result_mail-113.0.dist-info/entry_points.txt
avocado_framework_plugin_result_mail-113.0.dist-info/top_level.txt
avocado_framework_plugin_result_mail-113.0.dist-info/RECORD
